PlaygroundMR01-0.1.937.dist-info/METADATA
PlaygroundMR01-0.1.937.dist-info/WHEEL
PlaygroundMR01-0.1.937.dist-info/license_files/LICENSE
MRzeroCore/simulation/isochromat_sim.py
MRzeroCore/simulation/pre_pass.py
MRzeroCore/simulation/main_pass.py
MRzeroCore/reconstruction.py
MRzeroCore/sequence.py
MRzeroCore/phantom/custom_voxel_phantom.py
MRzeroCore/phantom/sim_data.py
MRzeroCore/phantom/voxel_grid_phantom.py
MRzeroCore/phantom/brainweb/brainweb_data_sources.txt
MRzeroCore/phantom/brainweb/output/.gitkeep
MRzeroCore/phantom/brainweb/brainweb_data.json
MRzeroCore/phantom/brainweb/__init__.py
MRzeroCore/pulseq/pulseq_loader/helpers.py
MRzeroCore/pulseq/pulseq_loader/pulse.py
MRzeroCore/pulseq/pulseq_loader/adc.py
MRzeroCore/pulseq/pulseq_loader/spoiler.py
MRzeroCore/pulseq/pulseq_loader/__init__.py
MRzeroCore/pulseq/pulseq_loader/pulseq_file/definitons.py
MRzeroCore/pulseq/pulseq_loader/pulseq_file/gradient.py
MRzeroCore/pulseq/pulseq_loader/pulseq_file/rf.py
MRzeroCore/pulseq/pulseq_loader/pulseq_file/trap.py
MRzeroCore/pulseq/pulseq_loader/pulseq_file/helpers.py
MRzeroCore/pulseq/pulseq_loader/pulseq_file/adc.py
MRzeroCore/pulseq/pulseq_loader/pulseq_file/block.py
MRzeroCore/pulseq/pulseq_loader/pulseq_file/__init__.py
MRzeroCore/pulseq/exporter_v2.py
MRzeroCore/pulseq/pulseq_exporter.py
MRzeroCore/pulseq/helpers.py
MRzeroCore/pulseq/exporter.py
MRzeroCore/util.py
MRzeroCore/__init__.py
MRzeroCore/_prepass.abi3.so
PlaygroundMR01-0.1.937.dist-info/RECORD
