Metadata-Version: 2.1
Name: PlaygroundMR01
Version: 0.1.937
Classifier: Programming Language :: Rust
Classifier: Programming Language :: Python :: Implementation :: CPython
Classifier: Programming Language :: Python :: Implementation :: PyPy
Classifier: License :: OSI Approved :: GNU Affero General Public License v3
Requires-Dist: torch>=1.12
Requires-Dist: pypulseq
Requires-Dist: matplotlib>=3.5
Requires-Dist: scipy>=1.7
Requires-Dist: requests>=2.20
Requires-Dist: scikit-image
Requires-Dist: torchkbnufft
Requires-Dist: pydisseqt>=0.1.4
License-File: LICENSE
Summary: PlaygroundMR0
Author-email: PlaygroundMR0 <playgroundmr0@gmail.com>
Requires-Python: >=3.9
Project-URL: Repository, https://github.com/playground-mr0/MRzeroCore
Project-URL: MRzero-Paper, https://arxiv.org/abs/2002.04265
Project-URL: Documentation, https://mrzero-core.readthedocs.io/
